colcon_ros_bazel/__init__.py
colcon_ros_bazel/argcomplete_completer/__init__.py
colcon_ros_bazel/argcomplete_completer/ros_bazel_args.py
colcon_ros_bazel/environment/__init__.py
colcon_ros_bazel/package_identification/__init__.py
colcon_ros_bazel/package_identification/ros_bazel.py
colcon_ros_bazel/task/__init__.py
colcon_ros_bazel/task/ros_bazel/__init__.py
colcon_ros_bazel/task/ros_bazel/build.py
colcon_ros_bazel/task/ros_bazel/test.py
colcon_ros_bazel-0.0.1.dist-info/METADATA
colcon_ros_bazel-0.0.1.dist-info/RECORD
colcon_ros_bazel-0.0.1.dist-info/WHEEL
colcon_ros_bazel-0.0.1.dist-info/entry_points.txt
colcon_ros_bazel-0.0.1.dist-info/top_level.txt
colcon_ros_bazel-0.0.1.dist-info/zip-safe
