Metadata-Version: 2.1
Name: colcon-ros-bazel
Version: 0.0.1
Summary: Extension for colcon to support ROS2 Bazel packages.
Home-page: https://colcon.readthedocs.io
Author: Mickael Gaillard
Author-email: mick.gaillard@gmail.com
Maintainer: Mickael Gaillard
Maintainer-email: mick.gaillard@gmail.com
License: Apache License, Version 2.0
Project-URL: Changelog, https://github.com/colcon/colcon-ros-bazel/milestones?state=closed
Project-URL: GitHub, https://github.com/colcon/colcon-ros-bazel/
Keywords: colcon
Platform: UNKNOWN
Classifier: Development Status :: 3 - Alpha
Classifier: Environment :: Plugins
Classifier: Intended Audience :: Developers
Classifier: License :: OSI Approved :: Apache Software License
Classifier: Operating System :: MacOS
Classifier: Operating System :: Microsoft :: Windows
Classifier: Operating System :: POSIX
Classifier: Programming Language :: Python
Classifier: Topic :: Software Development :: Build Tools
Requires-Dist: colcon-core
Requires-Dist: colcon-bazel (>=0.1.0)
Requires-Dist: colcon-library-path
Requires-Dist: colcon-ros (>=0.3.2)
